komoe_sass/__init__.py
komoe_sass-0.1.1.dist-info/METADATA
komoe_sass-0.1.1.dist-info/WHEEL
komoe_sass-0.1.1.dist-info/top_level.txt
komoe_sass-0.1.1.dist-info/RECORD
