Metadata-Version: 2.1
Name: komoe-sass
Version: 0.1.1
Summary: Sass plugin for komoe
Home-page: https://github.com/louisdevie/komoe-sass
Author: Louis DEVIE
License: Public domain
Keywords: komoe,sass,scss
Platform: UNKNOWN
Classifier: Development Status :: 4 - Beta
Classifier: License :: OSI Approved :: MIT License
Classifier: Programming Language :: Python :: 3.8
Requires-Python: >=3.8
Requires-Dist: Komoe (>=0.2.1)
